{
"type": "FeatureCollection",
"name": "H2A",
"crs": { "type": "name", "properties": { "name": "urn:ogc:def:crs:OGC:1.3:CRS84" } },
"features": [
{ "type": "Feature", "properties": { "id": 0 }, "geometry": { "type": "Point", "coordinates": [ -73.59960397651615, 45.562070618660293 ] } },
{ "type": "Feature", "properties": { "id": 1 }, "geometry": { "type": "Point", "coordinates": [ -73.594460583344897, 45.560066225823171 ] } },
{ "type": "Feature", "properties": { "id": 2 }, "geometry": { "type": "Point", "coordinates": [ -73.60365532145606, 45.564023395238486 ] } },
{ "type": "Feature", "properties": { "id": 3 }, "geometry": { "type": "Point", "coordinates": [ -73.604077621900359, 45.556355193379474 ] } },
{ "type": "Feature", "properties": { "id": 4 }, "geometry": { "type": "Point", "coordinates": [ -73.605063776649587, 45.56694884394819 ] } },
{ "type": "Feature", "properties": { "id": 5 }, "geometry": { "type": "Point", "coordinates": [ -73.602827201420709, 45.556577056115501 ] } },
{ "type": "Feature", "properties": { "id": 6 }, "geometry": { "type": "Point", "coordinates": [ -73.592103144832919, 45.567745398473569 ] } },
{ "type": "Feature", "properties": { "id": 7 }, "geometry": { "type": "Point", "coordinates": [ -73.596437957249918, 45.564390631161245 ] } },
{ "type": "Feature", "properties": { "id": 8 }, "geometry": { "type": "Point", "coordinates": [ -73.602245555662662, 45.559543419368119 ] } },
{ "type": "Feature", "properties": { "id": 9 }, "geometry": { "type": "Point", "coordinates": [ -73.601055122047185, 45.566299836331282 ] } },
{ "type": "Feature", "properties": { "id": 10 }, "geometry": { "type": "Point", "coordinates": [ -73.600842847191316, 45.555574335676141 ] } },
{ "type": "Feature", "properties": { "id": 11 }, "geometry": { "type": "Point", "coordinates": [ -73.594823817125246, 45.5689376188949 ] } },
{ "type": "Feature", "properties": { "id": 12 }, "geometry": { "type": "Point", "coordinates": [ -73.61070584189531, 45.558454007513305 ] } },
{ "type": "Feature", "properties": { "id": 13 }, "geometry": { "type": "Point", "coordinates": [ -73.598866147214423, 45.562649742146554 ] } },
{ "type": "Feature", "properties": { "id": 14 }, "geometry": { "type": "Point", "coordinates": [ -73.605259884026623, 45.559771290300112 ] } },
{ "type": "Feature", "properties": { "id": 15 }, "geometry": { "type": "Point", "coordinates": [ -73.594631524001173, 45.564717264708776 ] } },
{ "type": "Feature", "properties": { "id": 16 }, "geometry": { "type": "Point", "coordinates": [ -73.601903543263617, 45.560544118274706 ] } },
{ "type": "Feature", "properties": { "id": 17 }, "geometry": { "type": "Point", "coordinates": [ -73.59791105623745, 45.553316005129815 ] } },
{ "type": "Feature", "properties": { "id": 18 }, "geometry": { "type": "Point", "coordinates": [ -73.593264164528804, 45.565844326374425 ] } },
{ "type": "Feature", "properties": { "id": 19 }, "geometry": { "type": "Point", "coordinates": [ -73.599364133596509, 45.568698134086944 ] } },
{ "type": "Feature", "properties": { "id": 20 }, "geometry": { "type": "Point", "coordinates": [ -73.59593249852287, 45.559113725489041 ] } },
{ "type": "Feature", "properties": { "id": 21 }, "geometry": { "type": "Point", "coordinates": [ -73.596073178973185, 45.559342796133954 ] } }
]
}
