{
"type": "FeatureCollection",
"name": "H3B",
"crs": { "type": "name", "properties": { "name": "urn:ogc:def:crs:OGC:1.3:CRS84" } },
"features": [
{ "type": "Feature", "properties": { "id": 0 }, "geometry": { "type": "Point", "coordinates": [ -73.565385653979192, 45.504541320243156 ] } }
]
}
