{
"type": "FeatureCollection",
"name": "H4B",
"crs": { "type": "name", "properties": { "name": "urn:ogc:def:crs:OGC:1.3:CRS84" } },
"features": [
{ "type": "Feature", "properties": { "id": 0 }, "geometry": { "type": "Point", "coordinates": [ -73.63036630264385, 45.457220731022765 ] } },
{ "type": "Feature", "properties": { "id": 1 }, "geometry": { "type": "Point", "coordinates": [ -73.632146267234774, 45.461422637824917 ] } },
{ "type": "Feature", "properties": { "id": 2 }, "geometry": { "type": "Point", "coordinates": [ -73.63673081339185, 45.456681071049246 ] } },
{ "type": "Feature", "properties": { "id": 3 }, "geometry": { "type": "Point", "coordinates": [ -73.621355767854027, 45.463889638178699 ] } },
{ "type": "Feature", "properties": { "id": 4 }, "geometry": { "type": "Point", "coordinates": [ -73.642782109694309, 45.459179915547764 ] } },
{ "type": "Feature", "properties": { "id": 5 }, "geometry": { "type": "Point", "coordinates": [ -73.629278478232052, 45.456511873078306 ] } },
{ "type": "Feature", "properties": { "id": 6 }, "geometry": { "type": "Point", "coordinates": [ -73.632257065949247, 45.461612697152766 ] } },
{ "type": "Feature", "properties": { "id": 7 }, "geometry": { "type": "Point", "coordinates": [ -73.634740712833391, 45.463259550700378 ] } },
{ "type": "Feature", "properties": { "id": 8 }, "geometry": { "type": "Point", "coordinates": [ -73.632222186588052, 45.456934272086059 ] } },
{ "type": "Feature", "properties": { "id": 9 }, "geometry": { "type": "Point", "coordinates": [ -73.61893598562655, 45.463555927024004 ] } },
{ "type": "Feature", "properties": { "id": 10 }, "geometry": { "type": "Point", "coordinates": [ -73.624905855022675, 45.464190033296653 ] } },
{ "type": "Feature", "properties": { "id": 11 }, "geometry": { "type": "Point", "coordinates": [ -73.638678621192824, 45.464601507129274 ] } },
{ "type": "Feature", "properties": { "id": 12 }, "geometry": { "type": "Point", "coordinates": [ -73.627967806147666, 45.470495616660557 ] } },
{ "type": "Feature", "properties": { "id": 13 }, "geometry": { "type": "Point", "coordinates": [ -73.621896533231251, 45.46330632482222 ] } },
{ "type": "Feature", "properties": { "id": 14 }, "geometry": { "type": "Point", "coordinates": [ -73.633922787465764, 45.46475944753189 ] } },
{ "type": "Feature", "properties": { "id": 15 }, "geometry": { "type": "Point", "coordinates": [ -73.62340133993834, 45.459188327229207 ] } },
{ "type": "Feature", "properties": { "id": 16 }, "geometry": { "type": "Point", "coordinates": [ -73.619410674766797, 45.461231806303921 ] } },
{ "type": "Feature", "properties": { "id": 17 }, "geometry": { "type": "Point", "coordinates": [ -73.637703457358057, 45.466311495026339 ] } },
{ "type": "Feature", "properties": { "id": 18 }, "geometry": { "type": "Point", "coordinates": [ -73.635733065371539, 45.470693200782577 ] } },
{ "type": "Feature", "properties": { "id": 19 }, "geometry": { "type": "Point", "coordinates": [ -73.638076721636878, 45.46402284086377 ] } },
{ "type": "Feature", "properties": { "id": 20 }, "geometry": { "type": "Point", "coordinates": [ -73.631430884785658, 45.456266089482149 ] } },
{ "type": "Feature", "properties": { "id": 21 }, "geometry": { "type": "Point", "coordinates": [ -73.626711500282724, 45.468262449205483 ] } },
{ "type": "Feature", "properties": { "id": 22 }, "geometry": { "type": "Point", "coordinates": [ -73.631871990912998, 45.467256145873108 ] } },
{ "type": "Feature", "properties": { "id": 23 }, "geometry": { "type": "Point", "coordinates": [ -73.636876435504206, 45.465571700437486 ] } },
{ "type": "Feature", "properties": { "id": 24 }, "geometry": { "type": "Point", "coordinates": [ -73.63147401305622, 45.465240854900429 ] } },
{ "type": "Feature", "properties": { "id": 25 }, "geometry": { "type": "Point", "coordinates": [ -73.633669598534794, 45.453470396485734 ] } },
{ "type": "Feature", "properties": { "id": 26 }, "geometry": { "type": "Point", "coordinates": [ -73.629873077059798, 45.460667441834197 ] } },
{ "type": "Feature", "properties": { "id": 27 }, "geometry": { "type": "Point", "coordinates": [ -73.643731377095492, 45.459606049662895 ] } },
{ "type": "Feature", "properties": { "id": 28 }, "geometry": { "type": "Point", "coordinates": [ -73.633254277281083, 45.459364017538434 ] } },
{ "type": "Feature", "properties": { "id": 29 }, "geometry": { "type": "Point", "coordinates": [ -73.643008726266913, 45.45757927227271 ] } },
{ "type": "Feature", "properties": { "id": 30 }, "geometry": { "type": "Point", "coordinates": [ -73.625141055556341, 45.458245743259312 ] } }
]
}
