{
"type": "FeatureCollection",
"name": "H4M",
"crs": { "type": "name", "properties": { "name": "urn:ogc:def:crs:OGC:1.3:CRS84" } },
"features": [
{ "type": "Feature", "properties": { "id": 0 }, "geometry": { "type": "Point", "coordinates": [ -73.678851464676129, 45.50014336990094 ] } },
{ "type": "Feature", "properties": { "id": 1 }, "geometry": { "type": "Point", "coordinates": [ -73.689618415805, 45.500196851008234 ] } },
{ "type": "Feature", "properties": { "id": 2 }, "geometry": { "type": "Point", "coordinates": [ -73.695140317663203, 45.493929333862717 ] } },
{ "type": "Feature", "properties": { "id": 3 }, "geometry": { "type": "Point", "coordinates": [ -73.697559036292489, 45.497890551054184 ] } },
{ "type": "Feature", "properties": { "id": 4 }, "geometry": { "type": "Point", "coordinates": [ -73.693763244023984, 45.493783815008726 ] } },
{ "type": "Feature", "properties": { "id": 5 }, "geometry": { "type": "Point", "coordinates": [ -73.687544510489076, 45.506151884306568 ] } },
{ "type": "Feature", "properties": { "id": 6 }, "geometry": { "type": "Point", "coordinates": [ -73.691684821080571, 45.505546869908905 ] } },
{ "type": "Feature", "properties": { "id": 7 }, "geometry": { "type": "Point", "coordinates": [ -73.698286596983522, 45.500995616022195 ] } },
{ "type": "Feature", "properties": { "id": 8 }, "geometry": { "type": "Point", "coordinates": [ -73.676129179698364, 45.498145883016434 ] } },
{ "type": "Feature", "properties": { "id": 9 }, "geometry": { "type": "Point", "coordinates": [ -73.696246583957816, 45.494744486603381 ] } },
{ "type": "Feature", "properties": { "id": 10 }, "geometry": { "type": "Point", "coordinates": [ -73.683394154259901, 45.504868887340791 ] } },
{ "type": "Feature", "properties": { "id": 11 }, "geometry": { "type": "Point", "coordinates": [ -73.681556762815276, 45.500014965962457 ] } },
{ "type": "Feature", "properties": { "id": 12 }, "geometry": { "type": "Point", "coordinates": [ -73.69132794833736, 45.506142489860146 ] } },
{ "type": "Feature", "properties": { "id": 13 }, "geometry": { "type": "Point", "coordinates": [ -73.688489782702035, 45.500783349568991 ] } },
{ "type": "Feature", "properties": { "id": 14 }, "geometry": { "type": "Point", "coordinates": [ -73.687996130079, 45.495114040056961 ] } },
{ "type": "Feature", "properties": { "id": 15 }, "geometry": { "type": "Point", "coordinates": [ -73.688761466151604, 45.503011802015372 ] } },
{ "type": "Feature", "properties": { "id": 16 }, "geometry": { "type": "Point", "coordinates": [ -73.691329692588511, 45.501751350698989 ] } },
{ "type": "Feature", "properties": { "id": 17 }, "geometry": { "type": "Point", "coordinates": [ -73.683522745856962, 45.500943367046801 ] } },
{ "type": "Feature", "properties": { "id": 18 }, "geometry": { "type": "Point", "coordinates": [ -73.681575040965996, 45.497972105395704 ] } },
{ "type": "Feature", "properties": { "id": 19 }, "geometry": { "type": "Point", "coordinates": [ -73.677143704431543, 45.496500709817333 ] } },
{ "type": "Feature", "properties": { "id": 20 }, "geometry": { "type": "Point", "coordinates": [ -73.684246970669989, 45.50355888817662 ] } },
{ "type": "Feature", "properties": { "id": 21 }, "geometry": { "type": "Point", "coordinates": [ -73.692660400062792, 45.49772178028541 ] } },
{ "type": "Feature", "properties": { "id": 22 }, "geometry": { "type": "Point", "coordinates": [ -73.692982017267596, 45.499951613537668 ] } }
]
}
